xrdimageutil/__init__.py
xrdimageutil/roi.py
xrdimageutil/structures.py
xrdimageutil/utils.py
xrd_image_util-1.1.3.dist-info/LICENSE.txt
xrd_image_util-1.1.3.dist-info/METADATA
xrd_image_util-1.1.3.dist-info/WHEEL
xrd_image_util-1.1.3.dist-info/top_level.txt
xrd_image_util-1.1.3.dist-info/RECORD
