Metadata-Version: 2.1
Name: xrd-image-util
Version: 1.1.3
Summary: Utility package for handling XRD image data.
Author-email: Henry Smith <henryjsmith12@outlook.com>
License: Copyright (c) UChicago Argonne, LLC. All rights reserved.
Project-URL: Homepage, https://github.com/henryjsmith12/xrd-image-util
Project-URL: Bug Tracker, https://github.com/henryjsmith12/xrd-image-util/issues
Classifier: Development Status :: 1 - Planning
Classifier: Natural Language :: English
Classifier: Programming Language :: Python :: 3.8
Classifier: Programming Language :: Python :: 3.9
Classifier: Programming Language :: Python :: 3.10
Requires-Python: >=3.8
License-File: LICENSE.txt
Requires-Dist: apstools
Requires-Dist: area-detector-handlers
Requires-Dist: databroker (==1.2.5)
Requires-Dist: databroker-pack
Requires-Dist: bluesky
Requires-Dist: bluesky-live
Requires-Dist: dask
Requires-Dist: h5py
Requires-Dist: hdf5plugin
Requires-Dist: ophyd
Requires-Dist: polartools
Requires-Dist: prettytable
Requires-Dist: pyqt5
Requires-Dist: pyqtgraph
Requires-Dist: pyqtwebengine
Requires-Dist: pysumreg
Requires-Dist: scikit-image (==0.20.0)
Requires-Dist: scikit-learn
Requires-Dist: xrayutilities
Provides-Extra: test
Requires-Dist: coverage ; extra == 'test'
Requires-Dist: pytest ; extra == 'test'
